odoo/addons/account_reconcile_restrict_partner_mismatch/README.rst
odoo/addons/account_reconcile_restrict_partner_mismatch/__init__.py
odoo/addons/account_reconcile_restrict_partner_mismatch/__manifest__.py
odoo/addons/account_reconcile_restrict_partner_mismatch/i18n/account_reconcile_restrict_partner_mismatch.pot
odoo/addons/account_reconcile_restrict_partner_mismatch/models/__init__.py
odoo/addons/account_reconcile_restrict_partner_mismatch/models/account_move_line.py
odoo/addons/account_reconcile_restrict_partner_mismatch/readme/DESCRIPTION.rst
odoo/addons/account_reconcile_restrict_partner_mismatch/report/__init__.py
odoo/addons/account_reconcile_restrict_partner_mismatch/report/account_move_lines_report.xml
odoo/addons/account_reconcile_restrict_partner_mismatch/report/report_reconciled_lines.py
odoo/addons/account_reconcile_restrict_partner_mismatch/security/ir.model.access.csv
odoo/addons/account_reconcile_restrict_partner_mismatch/static/description/icon.png
odoo/addons/account_reconcile_restrict_partner_mismatch/static/description/index.html
odoo/addons/account_reconcile_restrict_partner_mismatch/tests/__init__.py
odoo/addons/account_reconcile_restrict_partner_mismatch/tests/test_reconciliation.py
odoo12_addon_account_reconcile_restrict_partner_mismatch-12.0.1.0.0.99.dev8.dist-info/METADATA
odoo12_addon_account_reconcile_restrict_partner_mismatch-12.0.1.0.0.99.dev8.dist-info/WHEEL
odoo12_addon_account_reconcile_restrict_partner_mismatch-12.0.1.0.0.99.dev8.dist-info/top_level.txt
odoo12_addon_account_reconcile_restrict_partner_mismatch-12.0.1.0.0.99.dev8.dist-info/RECORD
